oarepo_dashboard/__init__.py
oarepo_dashboard/i18n/__init__.py
oarepo_dashboard/i18n/webpack.py
oarepo_dashboard/i18n/semantic-ui/translations/oarepo_dashboard/i18next.js
oarepo_dashboard/i18n/semantic-ui/translations/oarepo_dashboard/messages/index.js
oarepo_dashboard/i18n/semantic-ui/translations/oarepo_dashboard/messages/cs/LC_MESSAGES/translations.json
oarepo_dashboard/i18n/semantic-ui/translations/oarepo_dashboard/messages/en/LC_MESSAGES/translations.json
oarepo_dashboard/i18n/translations/messages.mo
oarepo_dashboard/i18n/translations/messages.pot
oarepo_dashboard/i18n/translations/cs/LC_MESSAGES/messages.mo
oarepo_dashboard/i18n/translations/cs/LC_MESSAGES/messages.po
oarepo_dashboard/i18n/translations/en/LC_MESSAGES/messages.mo
oarepo_dashboard/i18n/translations/en/LC_MESSAGES/messages.po
oarepo_dashboard/ui/__init__.py
oarepo_dashboard/ui/dashboard_communities/__init__.py
oarepo_dashboard/ui/dashboard_communities/webpack.py
oarepo_dashboard/ui/dashboard_communities/semantic-ui/js/dashboard_communities/search/index.js
oarepo_dashboard/ui/dashboard_communities/templates/DashboardCommunitiesPage.jinja
oarepo_dashboard/ui/dashboard_components/__init__.py
oarepo_dashboard/ui/dashboard_components/search.py
oarepo_dashboard/ui/dashboard_components/webpack.py
oarepo_dashboard/ui/dashboard_components/semantic-ui/js/dashboard_components/custom-components.js
oarepo_dashboard/ui/dashboard_components/semantic-ui/js/dashboard_components/search/FacetsButtonGroupNameToggler.jsx
oarepo_dashboard/ui/dashboard_components/semantic-ui/js/dashboard_components/search/index.js
oarepo_dashboard/ui/dashboard_components/semantic-ui/less/custom-components.less
oarepo_dashboard/ui/dashboard_components/semantic-ui/less/oarepo_dashboard/themes/default/elements/button.overrides
oarepo_dashboard/ui/dashboard_components/semantic-ui/less/oarepo_dashboard/themes/default/elements/container.overrides
oarepo_dashboard-1.0.26.dist-info/METADATA
oarepo_dashboard-1.0.26.dist-info/WHEEL
oarepo_dashboard-1.0.26.dist-info/entry_points.txt
oarepo_dashboard-1.0.26.dist-info/top_level.txt
oarepo_dashboard-1.0.26.dist-info/RECORD
