Metadata-Version: 2.1
Name: oarepo-dashboard
Version: 1.0.26
Summary: Support for user dashboard (records, communities, requests)
Requires-Dist: oarepo-runtime>=1.4.44
Requires-Dist: openpyxl
Requires-Dist: oarepo-ui>=5.0.91
Requires-Dist: cachetools
Provides-Extra: dev
Requires-Dist: oarepo-tools; extra == "dev"
Provides-Extra: tests
Requires-Dist: pytest>=7.1.2; extra == "tests"
Requires-Dist: pytest-invenio; extra == "tests"
Requires-Dist: black; extra == "tests"
Requires-Dist: isort; extra == "tests"
Requires-Dist: autoflake; extra == "tests"
